Workbook

Sheet Dashboard
A1: Sales Revenue Tracker — Executive Dashboard
A4: H1 2026 (Jan – Jun) | Data source: Sales_Data sheet | Refresh: values recalc automatically
B7: Total Revenue | D7: Total Profit | F7: Overall Margin % | H7: Total Orders | J7: Avg Order Value
B9: =SUM(Sales_Data!L2:L221) -> 4628986 | D9: =SUM(Sales_Data!N2:N221) -> 1479278 | F9: =SUM(Sales_Data!N2:N221)/SUM(Sales_Data!L2:L221) -> 0.31956848 | H9: =COUNTA(Sales_Data!A2:A221) -> 220 | J9: =SUM(Sales_Data!L2:L221)/COUNTA(Sales_Data!A2:A221) -> 21040.845
B13: Performance Breakdown
B49: Target Achievement Snapshot (Latest Month: Jun-26)
B51: Jun-26 Target | D51: =Targets_vs_Actual!B10 -> 1150000
B52: Jun-26 Actual | D52: =Targets_vs_Actual!C10 -> 860824
B53: Jun-26 Achievement | D53: =Targets_vs_Actual!E10 -> 0.74854261
B54: H1 2026 Achievement | D54: =Targets_vs_Actual!C11/Targets_vs_Actual!B11 -> 0.75268065

Sheet ReadMe
A1: Sales Revenue Tracker System — User Guide
B4: Purpose
B5: This workbook is a complete, self-updating Sales Revenue Tracking system. Log every sale in one place and every report, KPI and chart in the workbook recalculates automatically.
B7: Who is this for
B8: Sales Operations, Regional Managers, and the Sales Manager reviewing team performance.
B11: Workbook Map
B12: Sheet | C12: What it contains | D12: Do you edit it?
B13: Dashboard | C13: Executive summary: KPIs, revenue trend, region/category/rep breakdowns. | D13: No — auto-updates
B14: Sales_Data | C14: One row per transaction — the single source of truth. Add new sales here. | D14: Yes — add new rows here
B15: Monthly_Summary | C15: Revenue, cost, profit and margin rolled up by month. | D15: No — auto-updates
B16: Regional_Summary | C16: Performance broken down by sales region. | D16: No — auto-updates
B17: Category_Summary | C17: Performance broken down by product category. | D17: No — auto-updates
B18: Rep_Performance | C18: Individual sales rep scorecard and ranking. | D18: No — auto-updates
B19: Targets_vs_Actual | C19: Monthly revenue target vs. actual achievement. | D19: Yes — edit Target column only
B22: How to add a new sale
B23: 1. Open the Sales_Data sheet.
B24: 2. Go to the first empty row at the bottom of the table.
B25: 3. Fill in Sale ID, Date, Region, Sales Rep, Category, Product, Units Sold, Unit Price and Unit Cost (blue cells only).
B26: 4. Revenue, Cost and Profit calculate automatically — do not type into those columns.
B27: 5. The Dashboard, Monthly_Summary, Regional_Summary, Category_Summary and Rep_Performance sheets update instantly.
B29: Color Key
B30: Blue text | C30: Editable input — safe to type over
B31: Black text | C31: Formula — do not overwrite
B32: Green text | C32: Link pulling from another sheet
B35: Last updated: 03-Jul-2026 | Version 1.0 | Owner: Sales Operations

Sheet Sales_Data
A1: Sale ID | B1: Date | C1: Month | D1: Region | E1: Sales Rep | F1: Category | G1: Product | H1: Customer Type | I1: Units Sold | J1: Unit Price (Rs.) | K1: Unit Cost (Rs.) | L1: Revenue (Rs.) | M1: Cost (Rs.) | N1: Profit (Rs.) | O1: Margin %
A2: SL-1038 | B2: 2026-01-01 | C2: =TEXT(B2,"mmm-yy") -> Jan-26 | D2: East | E2: Sourav Das | F2: Office Supplies | G2: Printer Paper (Box) | H2: Enterprise | I2: 6 | J2: 941 | K2: 679 | L2: =I2*J2 -> 5646 | M2: =I2*K2 -> 4074 | N2: =L2-M2 -> 1572 | O2: =IFERROR(N2/L2,0) -> 0.27842721
A3: SL-1021 | B3: 2026-01-02 | C3: =TEXT(B3,"mmm-yy") -> Jan-26 | D3: North | E3: Amit Sharma | F3: Furniture | G3: Office Chair | H3: New | I3: 3 | J3: 7470 | K3: 4438 | L3: =I3*J3 -> 22410 | M3: =I3*K3 -> 13314 | N3: =L3-M3 -> 9096 | O3: =IFERROR(N3/L3,0) -> 0.40589023
A4: SL-1145 | B4: 2026-01-02 | C4: =TEXT(B4,"mmm-yy") -> Jan-26 | D4: South | E4: Karthik Raman | F4: Accessories | G4: Cable Organizer | H4: New | I4: 1 | J4: 400 | K4: 291 | L4: =I4*J4 -> 400 | M4: =I4*K4 -> 291 | N4: =L4-M4 -> 109 | O4: =IFERROR(N4/L4,0) -> 0.2725
A5: SL-1014 | B5: 2026-01-03 | C5: =TEXT(B5,"mmm-yy") -> Jan-26 | D5: North | E5: Priya Nair | F5: Office Supplies | G5: Printer Paper (Box) | H5: Enterprise | I5: 1 | J5: 888 | K5: 596 | L5: =I5*J5 -> 888 | M5: =I5*K5 -> 596 | N5: =L5-M5 -> 292 | O5: =IFERROR(N5/L5,0) -> 0.32882883
A6: SL-1039 | B6: 2026-01-03 | C6: =TEXT(B6,"mmm-yy") -> Jan-26 | D6: North | E6: Amit Sharma | F6: Furniture | G6: Bookshelf | H6: New | I6: 3 | J6: 4300 | K6: 2995 | L6: =I6*J6 -> 12900 | M6: =I6*K6 -> 8985 | N6: =L6-M6 -> 3915 | O6: =IFERROR(N6/L6,0) -> 0.30348837
A7: SL-1154 | B7: 2026-01-06 | C7: =TEXT(B7,"mmm-yy") -> Jan-26 | D7: East | E7: Sourav Das | F7: Accessories | G7: Desk Lamp | H7: New | I7: 3 | J7: 1370 | K7: 819 | L7: =I7*J7 -> 4110 | M7: =I7*K7 -> 2457 | N7: =L7-M7 -> 1653 | O7: =IFERROR(N7/L7,0) -> 0.40218978
A8: SL-1128 | B8: 2026-01-09 | C8: =TEXT(B8,"mmm-yy") -> Jan-26 | D8: East | E8: Sourav Das | F8: Software | G8: Antivirus License | H8: Enterprise | I8: 3 | J8: 2150 | K8: 1290 | L8: =I8*J8 -> 6450 | M8: =I8*K8 -> 3870 | N8: =L8-M8 -> 2580 | O8: =IFERROR(N8/L8,0) -> 0.4
A9: SL-1108 | B9: 2026-01-10 | C9: =TEXT(B9,"mmm-yy") -> Jan-26 | D9: South | E9: Divya Menon | F9: Electronics | G9: Webcam HD | H9: New | I9: 5 | J9: 1830 | K9: 1067 | L9: =I9*J9 -> 9150 | M9: =I9*K9 -> 5335 | N9: =L9-M9 -> 3815 | O9: =IFERROR(N9/L9,0) -> 0.41693989
A10: SL-1126 | B10: 2026-01-10 | C10: =TEXT(B10,"mmm-yy") -> Jan-26 | D10: East | E10: Ananya Roy | F10: Electronics | G10: Wireless Mouse | H10: Returning | I10: 6 | J10: 783 | K10: 475 | L10: =I10*J10 -> 4698 | M10: =I10*K10 -> 2850 | N10: =L10-M10 -> 1848 | O10: =IFERROR(N10/L10,0) -> 0.39335888
A11: SL-1162 | B11: 2026-01-11 | C11: =TEXT(B11,"mmm-yy") -> Jan-26 | D11: West | E11: Rahul Mehta | F11: Office Supplies | G11: Whiteboard | H11: Returning | I11: 1 | J11: 1920 | K11: 1481 | L11: =I11*J11 -> 1920 | M11: =I11*K11 -> 1481 | N11: =L11-M11 -> 439 | O11: =IFERROR(N11/L11,0) -> 0.22864583
A12: SL-1107 | B12: 2026-01-12 | C12: =TEXT(B12,"mmm-yy") -> Jan-26 | D12: East | E12: Ananya Roy | F12: Software | G12: Antivirus License | H12: Returning | I12: 10 | J12: 2160 | K12: 1677 | L12: =I12*J12 -> 21600 | M12: =I12*K12 -> 16770 | N12: =L12-M12 -> 4830 | O12: =IFERROR(N12/L12,0) -> 0.22361111
A13: SL-1135 | B13: 2026-01-12 | C13: =TEXT(B13,"mmm-yy") -> Jan-26 | D13: East | E13: Ananya Roy | F13: Electronics | G13: Wireless Mouse | H13: New | I13: 4 | J13: 863 | K13: 574 | L13: =I13*J13 -> 3452 | M13: =I13*K13 -> 2296 | N13: =L13-M13 -> 1156 | O13: =IFERROR(N13/L13,0) -> 0.33487833
... A221: SL-1179 | B221: 2026-06-30 | C221: =TEXT(B221,"mmm-yy") -> Jun-26 | D221: West | E221: Sneha Kulkarni | F221: Accessories | G221: Laptop Bag | H221: New | I221: 1 | J221: 1920 | K221: 1212 | L221: =I221*J221 -> 1920 | M221: =I221*K221 -> 1212 | N221: =L221-M221 -> 708 | O221: =IFERROR(N221/L221,0) -> 0.36875

Sheet Monthly_Summary
A1: Monthly Revenue Summary
A4: Month | B4: Revenue (Rs.) | C4: Cost (Rs.) | D4: Profit (Rs.) | E4: Margin % | F4: Orders | G4: Avg Order Value (Rs.)
A5: Jan-26 | B5: =SUMIF(Sales_Data!$C$2:$C$221,$A5,Sales_Data!$L$2:$L$221) -> 918413 | C5: =SUMIF(Sales_Data!$C$2:$C$221,$A5,Sales_Data!$M$2:$M$221) -> 616128 | D5: =B5-C5 -> 302285 | E5: =IFERROR(D5/B5,0) -> 0.32913842 | F5: =COUNTIF(Sales_Data!$C$2:$C$221,$A5) -> 43 | G5: =IFERROR(B5/F5,0) -> 21358.442
A6: Feb-26 | B6: =SUMIF(Sales_Data!$C$2:$C$221,$A6,Sales_Data!$L$2:$L$221) -> 546647 | C6: =SUMIF(Sales_Data!$C$2:$C$221,$A6,Sales_Data!$M$2:$M$221) -> 380044 | D6: =B6-C6 -> 166603 | E6: =IFERROR(D6/B6,0) -> 0.30477255 | F6: =COUNTIF(Sales_Data!$C$2:$C$221,$A6) -> 24 | G6: =IFERROR(B6/F6,0) -> 22776.958
A7: Mar-26 | B7: =SUMIF(Sales_Data!$C$2:$C$221,$A7,Sales_Data!$L$2:$L$221) -> 857484 | C7: =SUMIF(Sales_Data!$C$2:$C$221,$A7,Sales_Data!$M$2:$M$221) -> 575586 | D7: =B7-C7 -> 281898 | E7: =IFERROR(D7/B7,0) -> 0.32875016 | F7: =COUNTIF(Sales_Data!$C$2:$C$221,$A7) -> 45 | G7: =IFERROR(B7/F7,0) -> 19055.2
A8: Apr-26 | B8: =SUMIF(Sales_Data!$C$2:$C$221,$A8,Sales_Data!$L$2:$L$221) -> 596093 | C8: =SUMIF(Sales_Data!$C$2:$C$221,$A8,Sales_Data!$M$2:$M$221) -> 406704 | D8: =B8-C8 -> 189389 | E8: =IFERROR(D8/B8,0) -> 0.3177172 | F8: =COUNTIF(Sales_Data!$C$2:$C$221,$A8) -> 36 | G8: =IFERROR(B8/F8,0) -> 16558.139
A9: May-26 | B9: =SUMIF(Sales_Data!$C$2:$C$221,$A9,Sales_Data!$L$2:$L$221) -> 849525 | C9: =SUMIF(Sales_Data!$C$2:$C$221,$A9,Sales_Data!$M$2:$M$221) -> 616019 | D9: =B9-C9 -> 233506 | E9: =IFERROR(D9/B9,0) -> 0.27486654 | F9: =COUNTIF(Sales_Data!$C$2:$C$221,$A9) -> 33 | G9: =IFERROR(B9/F9,0) -> 25743.182
A10: Jun-26 | B10: =SUMIF(Sales_Data!$C$2:$C$221,$A10,Sales_Data!$L$2:$L$221) -> 860824 | C10: =SUMIF(Sales_Data!$C$2:$C$221,$A10,Sales_Data!$M$2:$M$221) -> 555227 | D10: =B10-C10 -> 305597 | E10: =IFERROR(D10/B10,0) -> 0.3550052 | F10: =COUNTIF(Sales_Data!$C$2:$C$221,$A10) -> 39 | G10: =IFERROR(B10/F10,0) -> 22072.41
A11: Total | B11: =SUM(B5:B10) -> 4628986 | C11: =SUM(C5:C10) -> 3149708 | D11: =SUM(D5:D10) -> 1479278 | E11: =IFERROR(D11/B11,0) -> 0.31956848 | F11: =SUM(F5:F10) -> 220 | G11: =IFERROR(B11/F11,0) -> 21040.845

Sheet Regional_Summary
A1: Regional Performance Summary
A4: Region | B4: Revenue (Rs.) | C4: Profit (Rs.) | D4: Margin % | E4: Orders | F4: % of Total Revenue
A5: East | B5: =SUMIF(Sales_Data!$D$2:$D$221,$A5,Sales_Data!$L$2:$L$221) -> 1082994 | C5: =SUMIF(Sales_Data!$D$2:$D$221,$A5,Sales_Data!$N$2:$N$221) -> 348103 | D5: =IFERROR(C5/B5,0) -> 0.32142653 | E5: =COUNTIF(Sales_Data!$D$2:$D$221,$A5) -> 53 | F5: =IFERROR(B5/SUM($B$5:$B$8),0) -> 0.23395923
A6: North | B6: =SUMIF(Sales_Data!$D$2:$D$221,$A6,Sales_Data!$L$2:$L$221) -> 1310998 | C6: =SUMIF(Sales_Data!$D$2:$D$221,$A6,Sales_Data!$N$2:$N$221) -> 428838 | D6: =IFERROR(C6/B6,0) -> 0.32710805 | E6: =COUNTIF(Sales_Data!$D$2:$D$221,$A6) -> 54 | F6: =IFERROR(B6/SUM($B$5:$B$8),0) -> 0.28321494
A7: South | B7: =SUMIF(Sales_Data!$D$2:$D$221,$A7,Sales_Data!$L$2:$L$221) -> 1065360 | C7: =SUMIF(Sales_Data!$D$2:$D$221,$A7,Sales_Data!$N$2:$N$221) -> 340873 | D7: =IFERROR(C7/B7,0) -> 0.31996039 | E7: =COUNTIF(Sales_Data!$D$2:$D$221,$A7) -> 57 | F7: =IFERROR(B7/SUM($B$5:$B$8),0) -> 0.23014976
A8: West | B8: =SUMIF(Sales_Data!$D$2:$D$221,$A8,Sales_Data!$L$2:$L$221) -> 1169634 | C8: =SUMIF(Sales_Data!$D$2:$D$221,$A8,Sales_Data!$N$2:$N$221) -> 361464 | D8: =IFERROR(C8/B8,0) -> 0.30904026 | E8: =COUNTIF(Sales_Data!$D$2:$D$221,$A8) -> 56 | F8: =IFERROR(B8/SUM($B$5:$B$8),0) -> 0.25267607

Sheet Category_Summary
A1: Product Category Performance
A4: Category | B4: Revenue (Rs.) | C4: Profit (Rs.) | D4: Margin % | E4: Units Sold | F4: Orders
A5: Accessories | B5: =SUMIF(Sales_Data!$F$2:$F$221,$A5,Sales_Data!$L$2:$L$221) -> 184482 | C5: =SUMIF(Sales_Data!$F$2:$F$221,$A5,Sales_Data!$N$2:$N$221) -> 59078 | D5: =IFERROR(C5/B5,0) -> 0.3202372 | E5: =SUMIF(Sales_Data!$F$2:$F$221,$A5,Sales_Data!$I$2:$I$221) -> 170 | F5: =COUNTIF(Sales_Data!$F$2:$F$221,$A5) -> 48
A6: Electronics | B6: =SUMIF(Sales_Data!$F$2:$F$221,$A6,Sales_Data!$L$2:$L$221) -> 326195 | C6: =SUMIF(Sales_Data!$F$2:$F$221,$A6,Sales_Data!$N$2:$N$221) -> 102665 | D6: =IFERROR(C6/B6,0) -> 0.31473505 | E6: =SUMIF(Sales_Data!$F$2:$F$221,$A6,Sales_Data!$I$2:$I$221) -> 201 | F6: =COUNTIF(Sales_Data!$F$2:$F$221,$A6) -> 44
A7: Furniture | B7: =SUMIF(Sales_Data!$F$2:$F$221,$A7,Sales_Data!$L$2:$L$221) -> 1090280 | C7: =SUMIF(Sales_Data!$F$2:$F$221,$A7,Sales_Data!$N$2:$N$221) -> 367157 | D7: =IFERROR(C7/B7,0) -> 0.33675478 | E7: =SUMIF(Sales_Data!$F$2:$F$221,$A7,Sales_Data!$I$2:$I$221) -> 110 | F7: =COUNTIF(Sales_Data!$F$2:$F$221,$A7) -> 31
A8: Office Supplies | B8: =SUMIF(Sales_Data!$F$2:$F$221,$A8,Sales_Data!$L$2:$L$221) -> 198149 | C8: =SUMIF(Sales_Data!$F$2:$F$221,$A8,Sales_Data!$N$2:$N$221) -> 65606 | D8: =IFERROR(C8/B8,0) -> 0.33109428 | E8: =SUMIF(Sales_Data!$F$2:$F$221,$A8,Sales_Data!$I$2:$I$221) -> 184 | F8: =COUNTIF(Sales_Data!$F$2:$F$221,$A8) -> 46
A9: Software | B9: =SUMIF(Sales_Data!$F$2:$F$221,$A9,Sales_Data!$L$2:$L$221) -> 2829880 | C9: =SUMIF(Sales_Data!$F$2:$F$221,$A9,Sales_Data!$N$2:$N$221) -> 884772 | D9: =IFERROR(C9/B9,0) -> 0.31265354 | E9: =SUMIF(Sales_Data!$F$2:$F$221,$A9,Sales_Data!$I$2:$I$221) -> 189 | F9: =COUNTIF(Sales_Data!$F$2:$F$221,$A9) -> 51

Sheet Rep_Performance
A1: Sales Rep Performance Scorecard
A4: Sales Rep | B4: Region | C4: Revenue (Rs.) | D4: Profit (Rs.) | E4: Orders | F4: Avg Deal Size (Rs.) | G4: Rank
A5: Amit Sharma | B5: North | C5: =SUMIF(Sales_Data!$E$2:$E$221,$A5,Sales_Data!$L$2:$L$221) -> 689289 | D5: =SUMIF(Sales_Data!$E$2:$E$221,$A5,Sales_Data!$N$2:$N$221) -> 237557 | E5: =COUNTIF(Sales_Data!$E$2:$E$221,$A5) -> 29 | F5: =IFERROR(C5/E5,0) -> 23768.586 | G5: =RANK(C5,$C$5:$C$12) -> 2
A6: Ananya Roy | B6: East | C6: =SUMIF(Sales_Data!$E$2:$E$221,$A6,Sales_Data!$L$2:$L$221) -> 450232 | D6: =SUMIF(Sales_Data!$E$2:$E$221,$A6,Sales_Data!$N$2:$N$221) -> 142373 | E6: =COUNTIF(Sales_Data!$E$2:$E$221,$A6) -> 26 | F6: =IFERROR(C6/E6,0) -> 17316.615 | G6: =RANK(C6,$C$5:$C$12) -> 7
A7: Divya Menon | B7: South | C7: =SUMIF(Sales_Data!$E$2:$E$221,$A7,Sales_Data!$L$2:$L$221) -> 559756 | D7: =SUMIF(Sales_Data!$E$2:$E$221,$A7,Sales_Data!$N$2:$N$221) -> 161543 | E7: =COUNTIF(Sales_Data!$E$2:$E$221,$A7) -> 29 | F7: =IFERROR(C7/E7,0) -> 19301.931 | G7: =RANK(C7,$C$5:$C$12) -> 5
A8: Karthik Raman | B8: South | C8: =SUMIF(Sales_Data!$E$2:$E$221,$A8,Sales_Data!$L$2:$L$221) -> 505604 | D8: =SUMIF(Sales_Data!$E$2:$E$221,$A8,Sales_Data!$N$2:$N$221) -> 179330 | E8: =COUNTIF(Sales_Data!$E$2:$E$221,$A8) -> 28 | F8: =IFERROR(C8/E8,0) -> 18057.286 | G8: =RANK(C8,$C$5:$C$12) -> 6
A9: Priya Nair | B9: North | C9: =SUMIF(Sales_Data!$E$2:$E$221,$A9,Sales_Data!$L$2:$L$221) -> 621709 | D9: =SUMIF(Sales_Data!$E$2:$E$221,$A9,Sales_Data!$N$2:$N$221) -> 191281 | E9: =COUNTIF(Sales_Data!$E$2:$E$221,$A9) -> 25 | F9: =IFERROR(C9/E9,0) -> 24868.36 | G9: =RANK(C9,$C$5:$C$12) -> 4
A10: Rahul Mehta | B10: West | C10: =SUMIF(Sales_Data!$E$2:$E$221,$A10,Sales_Data!$L$2:$L$221) -> 858777 | D10: =SUMIF(Sales_Data!$E$2:$E$221,$A10,Sales_Data!$N$2:$N$221) -> 261471 | E10: =COUNTIF(Sales_Data!$E$2:$E$221,$A10) -> 32 | F10: =IFERROR(C10/E10,0) -> 26836.781 | G10: =RANK(C10,$C$5:$C$12) -> 1
A11: Sneha Kulkarni | B11: West | C11: =SUMIF(Sales_Data!$E$2:$E$221,$A11,Sales_Data!$L$2:$L$221) -> 310857 | D11: =SUMIF(Sales_Data!$E$2:$E$221,$A11,Sales_Data!$N$2:$N$221) -> 99993 | E11: =COUNTIF(Sales_Data!$E$2:$E$221,$A11) -> 24 | F11: =IFERROR(C11/E11,0) -> 12952.375 | G11: =RANK(C11,$C$5:$C$12) -> 8
A12: Sourav Das | B12: East | C12: =SUMIF(Sales_Data!$E$2:$E$221,$A12,Sales_Data!$L$2:$L$221) -> 632762 | D12: =SUMIF(Sales_Data!$E$2:$E$221,$A12,Sales_Data!$N$2:$N$221) -> 205730 | E12: =COUNTIF(Sales_Data!$E$2:$E$221,$A12) -> 27 | F12: =IFERROR(C12/E12,0) -> 23435.63 | G12: =RANK(C12,$C$5:$C$12) -> 3

Sheet Targets_vs_Actual
A1: Monthly Targets vs. Actual Revenue
A4: Month | B4: Target Revenue (Rs.) | C4: Actual Revenue (Rs.) | D4: Variance (Rs.) | E4: Achievement % | F4: Status
A5: Jan-26 | B5: 900000 | C5: =SUMIF(Sales_Data!$C$2:$C$221,$A5,Sales_Data!$L$2:$L$221) -> 918413 | D5: =C5-B5 -> 18413 | E5: =IFERROR(C5/B5,0) -> 1.0204589 | F5: =IF(E5>=1,"On Target",IF(E5>=0.9,"Near Target","Below Target")) -> On Target
A6: Feb-26 | B6: 950000 | C6: =SUMIF(Sales_Data!$C$2:$C$221,$A6,Sales_Data!$L$2:$L$221) -> 546647 | D6: =C6-B6 -> -403353 | E6: =IFERROR(C6/B6,0) -> 0.57541789 | F6: =IF(E6>=1,"On Target",IF(E6>=0.9,"Near Target","Below Target")) -> Below Target
A7: Mar-26 | B7: 1000000 | C7: =SUMIF(Sales_Data!$C$2:$C$221,$A7,Sales_Data!$L$2:$L$221) -> 857484 | D7: =C7-B7 -> -142516 | E7: =IFERROR(C7/B7,0) -> 0.857484 | F7: =IF(E7>=1,"On Target",IF(E7>=0.9,"Near Target","Below Target")) -> Below Target
A8: Apr-26 | B8: 1050000 | C8: =SUMIF(Sales_Data!$C$2:$C$221,$A8,Sales_Data!$L$2:$L$221) -> 596093 | D8: =C8-B8 -> -453907 | E8: =IFERROR(C8/B8,0) -> 0.56770762 | F8: =IF(E8>=1,"On Target",IF(E8>=0.9,"Near Target","Below Target")) -> Below Target
A9: May-26 | B9: 1100000 | C9: =SUMIF(Sales_Data!$C$2:$C$221,$A9,Sales_Data!$L$2:$L$221) -> 849525 | D9: =C9-B9 -> -250475 | E9: =IFERROR(C9/B9,0) -> 0.77229545 | F9: =IF(E9>=1,"On Target",IF(E9>=0.9,"Near Target","Below Target")) -> Below Target
A10: Jun-26 | B10: 1150000 | C10: =SUMIF(Sales_Data!$C$2:$C$221,$A10,Sales_Data!$L$2:$L$221) -> 860824 | D10: =C10-B10 -> -289176 | E10: =IFERROR(C10/B10,0) -> 0.74854261 | F10: =IF(E10>=1,"On Target",IF(E10>=0.9,"Near Target","Below Target")) -> Below Target
A11: Total | B11: =SUM(B5:B10) -> 6150000 | C11: =SUM(C5:C10) -> 4628986 | D11: =C11-B11 -> -1521014 | E11: =IFERROR(C11/B11,0) -> 0.75268065
